pzwin/Button.py
pzwin/Constants.py
pzwin/Dialog.py
pzwin/Edit.py
pzwin/Label.py
pzwin/Panel.py
pzwin/WinBase.py
pzwin/WinEvent.py
pzwin/WinFrame.py
pzwin/Window.py
pzwin/__init__.py
pzwin/pgzeroEntry.py
pzwin/fonts/arial.ttf
pzwin/fonts/msyh.ttc
pzwin/images/cross_down.png
pzwin/images/cross_over.png
pzwin/images/cross_up.png
pzwin/images/defaultIcon.png
pzwin/images/mousePointer2.png
pzwin-0.0.5.dist-info/LICENSE
pzwin-0.0.5.dist-info/METADATA
pzwin-0.0.5.dist-info/WHEEL
pzwin-0.0.5.dist-info/top_level.txt
pzwin-0.0.5.dist-info/RECORD
